{"closest_street": {"place_id": 14117293, "licence": "Data \u00a9 OpenStreetMap contributors, ODbL 1.0. https://osm.org/copyright", "osm_type": "node", "osm_id": 1308632690, "lat": "1.1045862", "lon": "109.8473035", "display_name": "Tamong, Seluas, Bengkayang, Kalimantan Barat, Indonesia", "address": {"village": "Tamong", "county": "Seluas", "state_district": "Bengkayang", "state": "Kalimantan Barat", "country": "Indonesia", "country_code": "id"}, "boundingbox": ["1.0845862", "1.1245862", "109.8273035", "109.8673035"]}, "closest_city": {"place_id": 274571567, "licence": "Data \u00a9 OpenStreetMap contributors, ODbL 1.0. https://osm.org/copyright", "osm_type": "relation", "osm_id": 10621600, "lat": "1.2062974999999998", "lon": "109.8223321460662", "display_name": "Seluas, Bengkayang, Kalimantan Barat, Indonesia", "address": {"county": "Seluas", "state_district": "Bengkayang", "state": "Kalimantan Barat", "country": "Indonesia", "country_code": "id"}, "boundingbox": ["1.0271976", "1.3854616", "109.5763746", "109.9575408"]}}